poetry_plugin_private/__init__.py
poetry_plugin_private/mirror_plugin.py
poetry_plugin_private/version_plugin.py
poetry_plugin_private-2.0.0.dist-info/entry_points.txt
poetry_plugin_private-2.0.0.dist-info/LICENSE
poetry_plugin_private-2.0.0.dist-info/METADATA
poetry_plugin_private-2.0.0.dist-info/WHEEL
poetry_plugin_private-2.0.0.dist-info/RECORD
