Metadata-Version: 2.3
Name: poetry-plugin-private
Version: 2.0.0
Summary: A plugin that contains dynamic version numbers and default PyPI repository source settings.
License: MIT
Author: L.STONE
Author-email: <web.developer.network@gmail.com>
Requires-Python: >=3.12,<4.0
Classifier: License :: OSI Approved :: MIT License
Classifier: Programming Language :: Python :: 3
Classifier: Programming Language :: Python :: 3.12
Classifier: Programming Language :: Python :: 3.13
Requires-Dist: poetry (>=2.0.0,<3.0.0)
